gymnasium/__init__.py
gymnasium/core.py
gymnasium/error.py
gymnasium/logger.py
gymnasium/py.typed
gymnasium/envs/__init__.py
gymnasium/envs/functional_jax_env.py
gymnasium/envs/registration.py
gymnasium/envs/box2d/__init__.py
gymnasium/envs/box2d/bipedal_walker.py
gymnasium/envs/box2d/car_dynamics.py
gymnasium/envs/box2d/car_racing.py
gymnasium/envs/box2d/lunar_lander.py
gymnasium/envs/classic_control/__init__.py
gymnasium/envs/classic_control/acrobot.py
gymnasium/envs/classic_control/cartpole.py
gymnasium/envs/classic_control/continuous_mountain_car.py
gymnasium/envs/classic_control/mountain_car.py
gymnasium/envs/classic_control/pendulum.py
gymnasium/envs/classic_control/utils.py
gymnasium/envs/classic_control/assets/clockwise.png
gymnasium/envs/mujoco/__init__.py
gymnasium/envs/mujoco/ant.py
gymnasium/envs/mujoco/ant_v3.py
gymnasium/envs/mujoco/ant_v4.py
gymnasium/envs/mujoco/ant_v5.py
gymnasium/envs/mujoco/half_cheetah.py
gymnasium/envs/mujoco/half_cheetah_v3.py
gymnasium/envs/mujoco/half_cheetah_v4.py
gymnasium/envs/mujoco/half_cheetah_v5.py
gymnasium/envs/mujoco/hopper.py
gymnasium/envs/mujoco/hopper_v3.py
gymnasium/envs/mujoco/hopper_v4.py
gymnasium/envs/mujoco/hopper_v5.py
gymnasium/envs/mujoco/humanoid.py
gymnasium/envs/mujoco/humanoid_v3.py
gymnasium/envs/mujoco/humanoid_v4.py
gymnasium/envs/mujoco/humanoid_v5.py
gymnasium/envs/mujoco/humanoidstandup.py
gymnasium/envs/mujoco/humanoidstandup_v4.py
gymnasium/envs/mujoco/humanoidstandup_v5.py
gymnasium/envs/mujoco/inverted_double_pendulum.py
gymnasium/envs/mujoco/inverted_double_pendulum_v4.py
gymnasium/envs/mujoco/inverted_double_pendulum_v5.py
gymnasium/envs/mujoco/inverted_pendulum.py
gymnasium/envs/mujoco/inverted_pendulum_v4.py
gymnasium/envs/mujoco/inverted_pendulum_v5.py
gymnasium/envs/mujoco/mujoco_env.py
gymnasium/envs/mujoco/mujoco_py_env.py
gymnasium/envs/mujoco/mujoco_rendering.py
gymnasium/envs/mujoco/pusher.py
gymnasium/envs/mujoco/pusher_v4.py
gymnasium/envs/mujoco/pusher_v5.py
gymnasium-1.0.0.dist-info/LICENSE
gymnasium-1.0.0.dist-info/METADATA
gymnasium-1.0.0.dist-info/WHEEL
gymnasium-1.0.0.dist-info/top_level.txt
gymnasium-1.0.0.dist-info/RECORD
