Metadata-Version: 2.1
Name: gymnasium
Version: 1.0.0
Summary: A standard API for reinforcement learning and a diverse set of reference environments (formerly Gym).
Author-email: Farama Foundation <contact@farama.org>
License: MIT License
Project-URL: Homepage, https://farama.org
Project-URL: Repository, https://github.com/Farama-Foundation/Gymnasium
Project-URL: Documentation, https://gymnasium.farama.org
Project-URL: Bug Report, https://github.com/Farama-Foundation/Gymnasium/issues
Keywords: Reinforcement Learning,game,RL,AI,gymnasium
Classifier: Development Status :: 5 - Production/Stable
Classifier: License :: OSI Approved :: MIT License
Classifier: Programming Language :: Python :: 3
Classifier: Programming Language :: Python :: 3.8
Classifier: Programming Language :: Python :: 3.9
Classifier: Programming Language :: Python :: 3.10
Classifier: Programming Language :: Python :: 3.11
Classifier: Programming Language :: Python :: 3.12
Classifier: Intended Audience :: Science/Research
Classifier: Topic :: Scientific/Engineering :: Artificial Intelligence
Requires-Python: >=3.8
License-File: LICENSE
Requires-Dist: numpy>=1.21.0
Requires-Dist: cloudpickle>=1.2.0
Requires-Dist: importlib-metadata>=4.8.0; python_version < "3.10"
Requires-Dist: typing-extensions>=4.3.0
Requires-Dist: farama-notifications>=0.0.1
Provides-Extra: atari
Requires-Dist: ale_py>=0.9; extra == "atari"
Provides-Extra: box2d
Requires-Dist: box2d-py==2.3.5; extra == "box2d"
Requires-Dist: pygame>=2.1.3; extra == "box2d"
Requires-Dist: swig==4.*; extra == "box2d"
Provides-Extra: classic-control
Requires-Dist: pygame>=2.1.3; extra == "classic-control"
Provides-Extra: classic-control
Requires-Dist: pygame>=2.1.3; extra == "classic-control"
Provides-Extra: mujoco-py
Requires-Dist: mujoco-py<2.2,>=2.1; extra == "mujoco-py"
Requires-Dist: cython<3; extra == "mujoco-py"
Provides-Extra: mujoco-py
Requires-Dist: mujoco-py<2.2,>=2.1; extra == "mujoco-py"
Requires-Dist: cython<3; extra == "mujoco-py"
Provides-Extra: mujoco
Requires-Dist: mujoco>=2.1.5; extra == "mujoco"
Requires-Dist: imageio>=2.14.1; extra == "mujoco"
Provides-Extra: toy-text
Requires-Dist: pygame>=2.1.3; extra == "toy-text"
Provides-Extra: toy-text
Requires-Dist: pygame>=2.1.3; extra == "toy-text"
Provides-Extra: jax
Requires-Dist: jax>=0.4.0; extra == "jax"
Requires-Dist: jaxlib>=0.4.0; extra == "jax"
Requires-Dist: flax>=0.5.0; extra == "jax"
Provides-Extra: torch
Requires-Dist: torch>=1.0.0; extra == "torch"
Provides-Extra: other
Requires-Dist: moviepy>=1.0.0; extra == "other"
Requires-Dist: matplotlib>=3.0; extra == "other"
Requires-Dist: opencv-python>=3.0; extra == "other"
Provides-Extra: all
Requires-Dist: ale_py>=0.9; extra == "all"
Requires-Dist: box2d-py==2.3.5; extra == "all"
Requires-Dist: pygame>=2.1.3; extra == "all"
Requires-Dist: swig==4.*; extra == "all"
Requires-Dist: pygame>=2.1.3; extra == "all"
Requires-Dist: mujoco-py<2.2,>=2.1; extra == "all"
Requires-Dist: cython<3; extra == "all"
Requires-Dist: mujoco>=2.1.5; extra == "all"
Requires-Dist: imageio>=2.14.1; extra == "all"
Requires-Dist: pygame>=2.1.3; extra == "all"
Requires-Dist: jax>=0.4.0; extra == "all"
Requires-Dist: jaxlib>=0.4.0; extra == "all"
Requires-Dist: flax>=0.5.0; extra == "all"
Requires-Dist: torch>=1.0.0; extra == "all"
Requires-Dist: opencv-python>=3.0; extra == "all"
Requires-Dist: matplotlib>=3.0; extra == "all"
Requires-Dist: moviepy>=1.0.0; extra == "all"
Provides-Extra: testing
Requires-Dist: pytest==7.1.3; extra == "testing"
Requires-Dist: scipy>=1.7.3; extra == "testing"
Requires-Dist: dill>=0.3.7; extra == "testing"
